drugwars/__init__.py
drugwars/__main__.py
drugwars/classes.py
drugwars/events.py
drugwars/helpers.py
drugwars-1.2.1.post3.dist-info/LICENSE
drugwars-1.2.1.post3.dist-info/METADATA
drugwars-1.2.1.post3.dist-info/WHEEL
drugwars-1.2.1.post3.dist-info/entry_points.txt
drugwars-1.2.1.post3.dist-info/top_level.txt
drugwars-1.2.1.post3.dist-info/zip-safe
drugwars-1.2.1.post3.dist-info/RECORD
