Metadata-Version: 2.1
Name: drugwars
Version: 1.2.1.post3
Summary: The 80s DOS game re-written in Python
Home-page: https://github.com/M4cs/Drugwars
Author: Max Bridgland
Author-email: mabridgland@protonmail.com
License: GNU General Public License v3 (GPLv3) (GPL)
Platform: UNKNOWN
Classifier: Development Status :: 5 - Production/Stable
Classifier: Environment :: Console
Classifier: License :: OSI Approved :: GNU General Public License v3 or later (GPLv3+)
Classifier: Natural Language :: English
Classifier: Operating System :: Microsoft
Classifier: Operating System :: MacOS
Classifier: Operating System :: Unix
Classifier: Programming Language :: Python :: 3
Classifier: Programming Language :: Python :: Implementation :: CPython
Classifier: Topic :: Games/Entertainment :: Turn Based Strategy
Requires-Dist: terminaltables
Requires-Dist: requests
